[{"ISRC": "BER181131702",
 "mainArtist": "EX TEMPORE", 
 "featuredArtists": ["FLORIAN HEYERICK"],
 "title": "DURCH DIE HERZLICHE BARMHERZIGK", 
 "versionTitle": null, 
 "duration": 227, 
 "yearOfRecording": 2002, 
 "territoryOfRecording": "BE", 
 "languageOfPerformance": null, 
 "originalReleaseDate": "2002-01-01", 
 "originalReleaseLabel": "OUTHERE SA", 
 "creators": ["GOLDBERG JOHANN GOTTLIEB"],
 "isVideo": false,
 "releases": [{
    "title": "GOLDBERG  JL BACH & KREBS",
    "artist": null,
    "ICPN": "5400439003170",
    "numberOfTracks": null,
    "label": "RICERCAR",
    "duration": null,
    "isCompilation": false
 }]
},
{"ISRC": "ITHZ01301781",
 "mainArtist": "DROPS OF CHOCOLATE", 
 "featuredArtists": [],
 "title": "SWEET ECSTASY", 
 "versionTitle": null, 
 "duration": 299, 
 "yearOfRecording": 2016, 
 "territoryOfRecording": "IT", 
 "languageOfPerformance": null, 
 "originalReleaseDate": "2016-01-01", 
 "originalReleaseLabel": "SMILAX RECORDS", 
 "creators": [],
 "isVideo": false,
 "releases": []
}, 
{"ISRC": "ITHZ01300286",
 "mainArtist": "DINO MANNOCCHI", 
 "featuredArtists": [],
 "title": "SWEET ARMONY (TECHNOLOGY VRS)", 
 "versionTitle": null, 
 "duration": 420, 
 "yearOfRecording": 2016, 
 "territoryOfRecording": "IT", 
 "languageOfPerformance": null, 
 "originalReleaseDate": "2016-01-01", 
 "originalReleaseLabel": "SMILAX RECORDS", 
 "creators": [],
 "isVideo": false,
 "releases": [{
    "title": "SWEET ARMONY",
    "artist": null,
    "ICPN": "8033116079938",
    "numberOfTracks": null,
    "label": "2DJS4LOVE RECORDINGS",
    "duration": null,
    "isCompilation": false
 }]
},
{"ISRC": null,
 "mainArtist": "ORCHESTRE SYMPHONIQUE DE MONTREAL", 
 "featuredArtists": ["CHARLES DUTOIT"],
 "title": "PINI DI ROMA", 
 "versionTitle": null, 
 "duration": 300, 
 "yearOfRecording": 1982, 
 "territoryOfRecording": "CA", 
 "languageOfPerformance": null, 
 "originalReleaseDate": "1983-01-01", 
 "originalReleaseLabel": "DECCA", 
 "creators": ["RESPIGHI OTTORINO"],
 "isVideo": false,
 "releases": []
},
{"ISRC": null,
 "mainArtist": "ORCHESTRE SYMPHONIQUE DE MONTREAL", 
 "featuredArtists": ["CHARLES DUTOIT"],
 "title": "FESTE ROMANE", 
 "versionTitle": null, 
 "duration": 1493, 
 "yearOfRecording": 1982, 
 "territoryOfRecording": "CA", 
 "languageOfPerformance": null, 
 "originalReleaseDate": "1983-01-01", 
 "originalReleaseLabel": "DECCA", 
 "creators": ["RESPIGHI OTTORINO"],
 "isVideo": false,
 "releases": []
},
{"ISRC": "USAT21700437",
 "mainArtist": "Portugal. The Man", 
 "featuredArtists": [],
 "title": "Feel It Still", 
 "versionTitle": null, 
 "duration": 163, 
 "yearOfRecording": null, 
 "territoryOfRecording": null, 
 "languageOfPerformance": "ENG", 
 "originalReleaseDate": null, 
 "originalReleaseLabel": null, 
 "creators": ["Jason Sechrist", "Eric Howk", "Kyle O'Quin", "Zachary Carothers", "John Gourley", "Asa Taccone", "John Hill", "Robert Bateman", "Frederick Gorman", "Brian Holland"],
 "isVideo": false,
 "releases": [{
    "title": "RTL HITS 2017",
    "artist": "Various Artists",
    "ICPN": "886446459400",
    "numberOfTracks": 44,
    "label": "Sony Music Media",
    "duration": null,
    "isCompilation": true
 }]
},
{"ISRC": "GB28K1800010",
 "mainArtist": "David Guetta & Sia", 
 "featuredArtists": [],
 "title": "Flames", 
 "versionTitle": null, 
 "duration": 196, 
 "yearOfRecording": 2018, 
 "territoryOfRecording": null, 
 "languageOfPerformance": "ENG", 
 "originalReleaseDate": "2018-11-09", 
 "originalReleaseLabel": "What A Music Ltd", 
 "creators": ["Sia Furler", "Marcus van Wattum", "Giorgio Tuinfort", "David Guetta", "Chris Braide"],
 "isVideo": false,
 "releases": [{
    "title": "Flames",
    "artist": "David Guetta & Sia",
    "ICPN": "190295654924",
    "numberOfTracks": 1,
    "label": "Parlophone France",
    "duration": 196,
    "isCompilation": false
 }]
},
{"ISRC": "NOSTS0469020",
 "mainArtist": "YUICHIRO FUJIMOTO", 
 "featuredArtists": [],
 "title": "LITTLE SUNSET", 
 "versionTitle": null, 
 "duration": 179, 
 "yearOfRecording": 2002, 
 "territoryOfRecording": "JP", 
 "languageOfPerformance": null, 
 "originalReleaseDate": "2004-01-01", 
 "originalReleaseLabel": "SMALLTOWN SUPERSOUND", 
 "creators": [ ],
 "isVideo": false,
 "releases": [{
    "title": "KOMOREBI",
    "artist": null,
    "ICPN": "6001168369224",
    "numberOfTracks": 1,
    "label": "SMALLTOWN SUPERSOUND",
    "duration": null,
    "isCompilation": false
 }]
},
{"ISRC": "GBLZC1000005",
 "mainArtist": "IKONIKA", 
 "featuredArtists": [],
 "title": "A IKONOKLAST", 
 "versionTitle": null, 
 "duration": 141, 
 "yearOfRecording": 2010, 
 "territoryOfRecording": "GB", 
 "languageOfPerformance": null, 
 "originalReleaseDate": "2010-01-01", 
 "originalReleaseLabel": "HYPERDUB", 
 "creators": ["ABDEL HAMID"],
 "isVideo": false,
 "releases": [{
    "title": "IKONOKLAST EP",
    "artist": null,
    "ICPN": "5055300320797",
    "numberOfTracks": 1,
    "label": "HYPERDUB",
    "duration": null,
    "isCompilation": false
 }]
},
{"ISRC": "USYF71500026",
 "mainArtist": "ARIS KINDT", 
 "featuredArtists": [],
 "title": "BLUE SKY SHOES", 
 "versionTitle": "ORIGINAL MIX", 
 "duration": 413, 
 "yearOfRecording": 2015, 
 "territoryOfRecording": "US", 
 "languageOfPerformance": null, 
 "originalReleaseDate": "2015-01-01", 
 "originalReleaseLabel": "SCISSOR AND THREAD", 
 "creators": ["HEDRICK GABRIEL"],
 "isVideo": false,
 "releases": [{
    "title": "FLOODS",
    "artist": null,
    "ICPN": "4250382431558",
    "numberOfTracks": null,
    "label": "SCISSOR & THREAD",
    "duration": null,
    "isCompilation": false
 }]
}]